Ghidora/Ghidora.py
Ghidora/__init__.py
Ghidora-0.0.1.dist-info/LICENSE.txt
Ghidora-0.0.1.dist-info/METADATA
Ghidora-0.0.1.dist-info/WHEEL
Ghidora-0.0.1.dist-info/top_level.txt
Ghidora-0.0.1.dist-info/RECORD
