Metadata-Version: 2.1
Name: Ghidora
Version: 0.0.1
Summary: An abstract python library for calculating time complex math function.
Home-page: https://github.com/RankJay/Ghidora
Author: Jay Rank
Author-email: rank01jay01@gmail.com
License: UNKNOWN
Platform: UNKNOWN
Classifier: Programming Language :: Python :: 3
Classifier: License :: OSI Approved :: MIT License
Classifier: Operating System :: OS Independent
Requires-Python: >=3.6
